aiomongodel/__init__.py
aiomongodel/document.py
aiomongodel/errors.py
aiomongodel/fields.py
aiomongodel/queryset.py
aiomongodel/utils.py
aiomongodel-0.2.2.dist-info/LICENSE
aiomongodel-0.2.2.dist-info/METADATA
aiomongodel-0.2.2.dist-info/WHEEL
aiomongodel-0.2.2.dist-info/top_level.txt
aiomongodel-0.2.2.dist-info/RECORD
