Metadata-Version: 2.1
Name: aiomongodel
Version: 0.2.2
Summary: ODM to use with asynchronous MongoDB Motor driver.
Home-page: https://github.com/ilex/aiomongodel
Author: ilex
Author-email: ilexhostmaster@gmail.com
License: MIT
Classifier: Development Status :: 3 - Alpha
Classifier: Intended Audience :: Developers
Classifier: Topic :: Database
Classifier: License :: OSI Approved :: MIT License
Classifier: Programming Language :: Python :: 3 :: Only
Classifier: Programming Language :: Python :: 3.5
Classifier: Programming Language :: Python :: 3.6
Classifier: Programming Language :: Python :: 3.7
Classifier: Programming Language :: Python :: 3.8
Classifier: Programming Language :: Python :: 3.9
Classifier: Programming Language :: Python :: 3.10
Classifier: Programming Language :: Python :: 3.11
License-File: LICENSE
Requires-Dist: motor (<4.0,>=2.0)
